tests/__init__.py
tests/test_result_types.py
tests/test_search.py
uyts/__init__.py
uyts/search.py
uyts/server.py
unlimited_youtube_search-0.1.2.dist-info/LICENSE
unlimited_youtube_search-0.1.2.dist-info/METADATA
unlimited_youtube_search-0.1.2.dist-info/WHEEL
unlimited_youtube_search-0.1.2.dist-info/top_level.txt
unlimited_youtube_search-0.1.2.dist-info/RECORD
