Metadata-Version: 2.1
Name: unlimited-youtube-search
Version: 0.1.2
Summary: Search YouTube without YouTube Data API
Home-page: https://github.com/w-henderson/unlimited-youtube-search
Author: William Henderson
Author-email: william-henderson@outlook.com
License: UNKNOWN
Platform: UNKNOWN
Classifier: Programming Language :: Python :: 3
Classifier: License :: OSI Approved :: GNU General Public License v3 or later (GPLv3+)
Classifier: Operating System :: OS Independent
Requires-Python: >=3.6
Requires-Dist: requests
